je_mail_thunder/__init__.py
je_mail_thunder/__main__.py
je_mail_thunder/imap/__init__.py
je_mail_thunder/imap/imap_wrapper.py
je_mail_thunder/smtp/__init__.py
je_mail_thunder/smtp/smtp_wrapper.py
je_mail_thunder/utils/__init__.py
je_mail_thunder/utils/exception/__init__.py
je_mail_thunder/utils/exception/exception_tags.py
je_mail_thunder/utils/exception/exceptions.py
je_mail_thunder/utils/executor/__init__.py
je_mail_thunder/utils/executor/action_executor.py
je_mail_thunder/utils/file_process/__init__.py
je_mail_thunder/utils/file_process/get_dir_file_list.py
je_mail_thunder/utils/json/__init__.py
je_mail_thunder/utils/json/json_file.py
je_mail_thunder/utils/json_format/__init__.py
je_mail_thunder/utils/json_format/json_process.py
je_mail_thunder/utils/logging/__init__.py
je_mail_thunder/utils/logging/loggin_instance.py
je_mail_thunder/utils/package_manager/__init__.py
je_mail_thunder/utils/package_manager/package_manager_class.py
je_mail_thunder/utils/project/__init__.py
je_mail_thunder/utils/project/create_project_structure.py
je_mail_thunder/utils/project/template/__init__.py
je_mail_thunder/utils/project/template/template_executor.py
je_mail_thunder/utils/project/template/template_keyword.py
je_mail_thunder/utils/save_mail_user_content/__init__.py
je_mail_thunder/utils/save_mail_user_content/mail_thunder_content_data.py
je_mail_thunder/utils/save_mail_user_content/mail_thunder_content_save.py
je_mail_thunder/utils/save_mail_user_content/save_on_env.py
je_mail_thunder/utils/socket_server/__init__.py
je_mail_thunder/utils/socket_server/mail_thunder_socket_server.py
je_mail_thunder-0.0.23.dist-info/LICENSE
je_mail_thunder-0.0.23.dist-info/METADATA
je_mail_thunder-0.0.23.dist-info/WHEEL
je_mail_thunder-0.0.23.dist-info/top_level.txt
je_mail_thunder-0.0.23.dist-info/RECORD
