Metadata-Version: 2.1
Name: je_mail_thunder
Version: 0.0.23
Author-email: JE-Chen <jechenmailman@gmail.com>
License: MIT
Project-URL: Homepage, https://github.com/Intergration-Automation-Testing/MailThunder
Classifier: Programming Language :: Python :: 3.9
Classifier: Development Status :: 2 - Pre-Alpha
Classifier: Environment :: Win32 (MS Windows)
Classifier: Environment :: MacOS X
Classifier: Environment :: X11 Applications
Classifier: License :: OSI Approved :: MIT License
Classifier: Operating System :: OS Independent
Requires-Python: >=3.9
License-File: LICENSE
